coalg/__init__.py
coalg-0.0.0.dist-info/LICENSE
coalg-0.0.0.dist-info/METADATA
coalg-0.0.0.dist-info/WHEEL
coalg-0.0.0.dist-info/top_level.txt
coalg-0.0.0.dist-info/RECORD
